{
  "project_info": {
    "project_number": "297515883518",
    "project_id": "spark-1e73f",
    "storage_bucket": "spark-1e73f.appspot.com"
  },
  "client": [
    {
      "client_info": {
        "mobilesdk_app_id": "1:297515883518:android:60933cefd03014250cfeaf",
        "android_client_info": {
          "package_name": "host.exp.exponent"
        }
      },
      "oauth_client": [
        {
          "client_id": "297515883518-mk3b0licousgn1ed42tbntrbhjnldd4d.apps.googleusercontent.com",
          "client_type": 1,
          "android_info": {
            "package_name": "host.exp.exponent",
            "certificate_hash": "fd75ad2cf7b400007b4721ca3f36f6ba160978be"
          }
        }
      ],
      "api_key": [
        {
          "current_key": "AIzaSyC5NAalXGb8ssJwKL5_iL2smr32YyLJtGA"
        }
      ],
      "services": {
        "appinvite_service": {
          "other_platform_oauth_client": []
        }
      }
    }
  ],
  "configuration_version": "1"
}